gpt_cli/__init__.py
gpt_prompts/__init__.py
GPT_prompts-0.1.3.dist-info/LICENSE
GPT_prompts-0.1.3.dist-info/METADATA
GPT_prompts-0.1.3.dist-info/WHEEL
GPT_prompts-0.1.3.dist-info/entry_points.txt
GPT_prompts-0.1.3.dist-info/top_level.txt
GPT_prompts-0.1.3.dist-info/RECORD
