Metadata-Version: 2.1
Name: GPT-prompts
Version: 0.1.3
License-File: LICENSE
Requires-Dist: langchain
Requires-Dist: openai
